cdk8s_cluster_autoscaler_aws/__init__.py
cdk8s_cluster_autoscaler_aws/py.typed
cdk8s_cluster_autoscaler_aws/_jsii/__init__.py
cdk8s_cluster_autoscaler_aws/_jsii/cdk8s-cluster-autoscaler-aws@0.1.4.jsii.tgz
cdk8s_cluster_autoscaler_aws-0.1.4.dist-info/LICENSE
cdk8s_cluster_autoscaler_aws-0.1.4.dist-info/METADATA
cdk8s_cluster_autoscaler_aws-0.1.4.dist-info/WHEEL
cdk8s_cluster_autoscaler_aws-0.1.4.dist-info/top_level.txt
cdk8s_cluster_autoscaler_aws-0.1.4.dist-info/RECORD
